.DS_Store
sui/.DS_Store
sui/__init__.py
sui/dataset.py
sui/dl.py
sui/rl.py
sui/dl/__init__.py
sui/dl/afm.py
sui/dl/bert4rec.py
sui/dl/initializers.py
sui/dl/losses.py
sui/dl/nn.py
sui/dl/optimizers.py
sui/dl/pnn.py
sui/graph/__init__.py
sui/graph/deepwalk.py
sui/ml/__init__.py
sui/ml/afm.py
sui/ml/fm.py
sui/ml/mf.py
sui/ml/matrix_factorization/__init__.py
sui/ml/matrix_factorization/als.py
sui/ml/matrix_factorization/biassvd.py
sui/ml/matrix_factorization/bpr.py
sui/ml/matrix_factorization/funksvd.py
sui/ml/matrix_factorization/svd.py
sui/ml/matrix_factorization/svdpp.py
sui/rl/__init__.py
sui/rl/dqn.py
sui/toolbox/__init__.py
sui/toolbox/build_series_data.py
sui/toolbox/dataset.py
sui/toolbox/preprocessing.py
sui/toolbox/top_k.py
sui/toolbox/visualization.py
sui-0.1.13.dist-info/LICENSE
sui-0.1.13.dist-info/METADATA
sui-0.1.13.dist-info/WHEEL
sui-0.1.13.dist-info/top_level.txt
sui-0.1.13.dist-info/RECORD
